morstar_flask_restful/__init__.py
morstar_flask_restful/mixin.py
morstar_flask_restful-0.0.1.dist-info/LICENSE.md
morstar_flask_restful-0.0.1.dist-info/METADATA
morstar_flask_restful-0.0.1.dist-info/WHEEL
morstar_flask_restful-0.0.1.dist-info/entry_points.txt
morstar_flask_restful-0.0.1.dist-info/top_level.txt
morstar_flask_restful-0.0.1.dist-info/RECORD
